Mochgir-0.736.dist-info/METADATA
Mochgir-0.736.dist-info/RECORD
Mochgir-0.736.dist-info/WHEEL
Mochgir-0.736.dist-info/top_level.txt
mochgir/__init__.py
mochgir/mochgir.py
mochgir/conf/__init__.py
mochgir/conf/consts.py
mochgir/conf/font/__init__.py
