Metadata-Version: 2.1
Name: Mochgir
Version: 0.736
Summary: Translate and Analyze docx documents
Home-page: https://www.github.com/javadmokhtari/github
Author: Javad Mokhtari Koushyar
License: MIT
Platform: UNKNOWN
Requires-Python: >=3.0
Requires-Dist: requests (==2.19.1)
Requires-Dist: python-docx (==0.8.6)
Requires-Dist: google (==2.0.1)
Requires-Dist: reportlab (==3.4.0)
